Metadata-Version: 2.4
Name: groundeddino-vl
Version: 2025.11.0
Summary: GroundedDINO-VL - Modern Vision-Language Foundation Models for PyTorch 2.7 + CUDA 12.8
Author-email: ghostcipher1 <ghostcipher1@users.noreply.github.com>
Maintainer-email: ghostcipher1 <ghostcipher1@users.noreply.github.com>
License: Apache-2.0
Project-URL: Homepage, https://github.com/ghostcipher1/GroundedDINO-VL
Project-URL: Repository, https://github.com/ghostcipher1/GroundedDINO-VL
Project-URL: Issue Tracker, https://github.com/ghostcipher1/GroundedDINO-VL/issues
Project-URL: Documentation, https://github.com/ghostcipher1/GroundedDINO-VL#readme
Project-URL: Original Source, https://github.com/IDEA-Research/GroundingDINO
Project-URL: Legacy Fork, https://github.com/ghostcipher1/groundingdino-cu128
Keywords: groundeddino-vl,groundeddino_vl,computer-vision,object-detection,grounding,vision-language,transformer,pytorch,cuda,groundingdino
Classifier: Development Status :: 4 - Beta
Classifier: Intended Audience :: Developers
Classifier: Intended Audience :: Science/Research
Classifier: License :: OSI Approved :: Apache Software License
Classifier: Operating System :: POSIX :: Linux
Classifier: Programming Language :: Python :: 3
Classifier: Programming Language :: Python :: 3.9
Classifier: Programming Language :: Python :: 3.10
Classifier: Programming Language :: Python :: 3.11
Classifier: Programming Language :: Python :: 3.12
Classifier: Topic :: Scientific/Engineering :: Artificial Intelligence
Classifier: Topic :: Scientific/Engineering :: Image Recognition
Requires-Python: >=3.9
License-File: LICENSE
License-File: NOTICE
Requires-Dist: torch<2.8,>=2.7.0
Requires-Dist: torchvision>=0.18.0
Requires-Dist: transformers>=4.0
Requires-Dist: addict>=2.0
Requires-Dist: yapf>=0.30
Requires-Dist: timm>=0.6
Requires-Dist: numpy>=1.19
Requires-Dist: opencv-python>=4.5
Requires-Dist: supervision>=0.26.1
Requires-Dist: pycocotools>=2.0
Provides-Extra: dev
Requires-Dist: pytest>=7.0; extra == "dev"
Requires-Dist: pytest-cov>=4.0; extra == "dev"
Requires-Dist: flake8>=6.0; extra == "dev"
Requires-Dist: black==25.11.0; extra == "dev"
Requires-Dist: isort>=5.12; extra == "dev"
Requires-Dist: mypy>=1.0; extra == "dev"
Requires-Dist: pylint>=2.17; extra == "dev"
Requires-Dist: bandit>=1.7; extra == "dev"
Requires-Dist: safety>=2.3; extra == "dev"
Requires-Dist: build>=1.0; extra == "dev"
Requires-Dist: twine>=4.0; extra == "dev"
Provides-Extra: onnx
Requires-Dist: onnx>=1.12; extra == "onnx"
Requires-Dist: onnxruntime>=1.14; extra == "onnx"
Provides-Extra: trt
Provides-Extra: jetson
Dynamic: license-file
